{
    "movie": {
        "Duration": 840.10595703125,
        "NumFrames": 25178,
        "URL": "/RS03ASHS/PN03B/06-CAMHDA301/2016/01/16/CAMHDA301-20160116T180000Z.mov",
        "cacheURL": "http://lazycache_nocache:8080/v1/org/oceanobservatories/rawdata/files//RS03ASHS/PN03B/06-CAMHDA301/2016/01/16/CAMHDA301-20160116T180000Z.mov"
    },
    "contents": {
        "regions": "1.0"
    },
    "regions": [
        {
            "bounds": [
                581,
                1051
            ],
            "type": "static",
            "stats": {
                "scale_mean": 0.9999357818895359,
                "tx_mean": 0.012696094902670148,
                "ty_mean": -0.009561134637857889,
                "size": 658
            }
        },
        {
            "bounds": [
                1061,
                1251
            ],
            "type": "unknown",
            "stat": {
                "scale_mean": 1.0293292005816508,
                "tx_mean": 2.2135681622064327,
                "ty_mean": -1.070232613440259,
                "size": 266
            }
        },
        {
            "bounds": [
                1251,
                1351
            ],
            "type": "static",
            "stats": {
                "scale_mean": 0.9999579667891167,
                "tx_mean": -0.001121280214807744,
                "ty_mean": -0.0011264992155182532,
                "size": 140
            }
        },
        {
            "bounds": [
                1361,
                1711
            ],
            "type": "N",
            "stat": {
                "scale_mean": 0.9699975336276072,
                "tx_mean": -0.5676794344048186,
                "ty_mean": 21.10486905503968,
                "size": 490
            }
        },
        {
            "bounds": [
                1711,
                2151
            ],
            "type": "static",
            "stats": {
                "scale_mean": 1.0000117832940782,
                "tx_mean": 0.015204135923321276,
                "ty_mean": 0.07756348609010133,
                "size": 616
            }
        },
        {
            "bounds": [
                2161,
                2491
            ],
            "type": "NW",
            "stat": {
                "scale_mean": 1.0178553048426644,
                "tx_mean": 21.082215656851442,
                "ty_mean": 25.869422441420657,
                "size": 462
            }
        },
        {
            "bounds": [
                2491,
                2541
            ],
            "type": "static",
            "stats": {
                "scale_mean": 0.9959638130136937,
                "tx_mean": -2.611593587084996,
                "ty_mean": 0.5660073863780395,
                "size": 70
            }
        },
        {
            "bounds": [
                2551,
                2561
            ],
            "type": "unknown",
            "stat": {
                "scale_mean": 0.976091394500487,
                "tx_mean": 9.47623056347255,
                "ty_mean": 4.68385399872497,
                "size": 14
            }
        },
        {
            "bounds": [
                2561,
                2571
            ],
            "type": "static",
            "stats": {
                "scale_mean": 0.990748153747183,
                "tx_mean": -0.783862799246174,
                "ty_mean": -0.2701520121634,
                "size": 14
            }
        },
        {
            "bounds": [
                2581,
                2611
            ],
            "type": "W",
            "stat": {
                "scale_mean": 1.0126727472564667,
                "tx_mean": 10.003115131348334,
                "ty_mean": -1.3911321146589364,
                "size": 42
            }
        },
        {
            "bounds": [
                2611,
                2731
            ],
            "type": "static",
            "stats": {
                "scale_mean": 0.9992061358378,
                "tx_mean": 0.5737004546389562,
                "ty_mean": 0.2185228250173232,
                "size": 168
            }
        },
        {
            "bounds": [
                2741,
                2891
            ],
            "type": "zoom_in",
            "stat": {
                "scale_mean": 1.0638915071433925,
                "tx_mean": 4.874908761080826,
                "ty_mean": 2.580228454933955,
                "size": 210
            }
        },
        {
            "bounds": [
                2891,
                3781
            ],
            "type": "static",
            "stats": {
                "scale_mean": 0.9998385245694881,
                "tx_mean": 0.11760134933183393,
                "ty_mean": 0.07971750060739025,
                "size": 1246
            }
        },
        {
            "bounds": [
                3791,
                3951
            ],
            "type": "zoom_out",
            "stat": {
                "scale_mean": 0.9430100861685671,
                "tx_mean": -8.4075069758221,
                "ty_mean": 0.7034800622894974,
                "size": 224
            }
        },
        {
            "bounds": [
                3951,
                4121
            ],
            "type": "static",
            "stats": {
                "scale_mean": 0.9998930169829103,
                "tx_mean": 0.08303577662663926,
                "ty_mean": 0.007594006869727532,
                "size": 238
            }
        },
        {
            "bounds": [
                4131,
                4141
            ],
            "type": "NW",
            "stat": {
                "scale_mean": 0.5,
                "tx_mean": 289.903552595076,
                "ty_mean": 71.6632957451195,
                "size": 14
            }
        },
        {
            "bounds": [
                4141,
                4161
            ],
            "type": "static",
            "stats": {
                "scale_mean": 1.00002639276113,
                "tx_mean": 0.004717012746235805,
                "ty_mean": 0.006902724524540219,
                "size": 28
            }
        },
        {
            "bounds": [
                4171,
                4211
            ],
            "type": "SE",
            "stat": {
                "scale_mean": 1.0480696129863,
                "tx_mean": -29.25360248606535,
                "ty_mean": -19.197598356775423,
                "size": 56
            }
        },
        {
            "bounds": [
                4211,
                4301
            ],
            "type": "static",
            "stats": {
                "scale_mean": 1.001905626252769,
                "tx_mean": -1.3984784008847204,
                "ty_mean": -0.7297456142819089,
                "size": 126
            }
        },
        {
            "bounds": [
                4311,
                4581
            ],
            "type": "SE",
            "stat": {
                "scale_mean": 0.9786839884095258,
                "tx_mean": -23.612226437645806,
                "ty_mean": -35.755901487173794,
                "size": 378
            }
        },
        {
            "bounds": [
                4581,
                4881
            ],
            "type": "static",
            "stats": {
                "scale_mean": 1.0000051276187896,
                "tx_mean": 1.4026972907178306,
                "ty_mean": -0.4415437931686142,
                "size": 420
            }
        },
        {
            "bounds": [
                4891,
                5141
            ],
            "type": "N",
            "stat": {
                "scale_mean": 1.0016471240109204,
                "tx_mean": 6.732561075227523,
                "ty_mean": 41.944458526730976,
                "size": 350
            }
        },
        {
            "bounds": [
                5141,
                5421
            ],
            "type": "static",
            "stats": {
                "scale_mean": 1.0004391896918878,
                "tx_mean": -1.1188694130641268,
                "ty_mean": -0.3208193340556827,
                "size": 392
            }
        },
        {
            "bounds": [
                5431,
                5591
            ],
            "type": "zoom_in",
            "stat": {
                "scale_mean": 1.0651892318670357,
                "tx_mean": 2.176656551595845,
                "ty_mean": 1.2249983785164378,
                "size": 224
            }
        },
        {
            "bounds": [
                5591,
                5721
            ],
            "type": "static",
            "stats": {
                "scale_mean": 0.999983971156426,
                "tx_mean": 0.024718679591582287,
                "ty_mean": -0.02039731828041904,
                "size": 182
            }
        },
        {
            "bounds": [
                5731,
                5881
            ],
            "type": "zoom_in",
            "stat": {
                "scale_mean": 1.0796956103806181,
                "tx_mean": 1.2782595535912165,
                "ty_mean": -2.205195928198808,
                "size": 210
            }
        },
        {
            "bounds": [
                5881,
                6781
            ],
            "type": "static",
            "stats": {
                "scale_mean": 0.9999912990026867,
                "tx_mean": 0.0069053780687581825,
                "ty_mean": 0.016492640196338126,
                "size": 1260
            }
        },
        {
            "bounds": [
                6791,
                7081
            ],
            "type": "zoom_out",
            "stat": {
                "scale_mean": 0.9270673226077706,
                "tx_mean": -1.5158651162589563,
                "ty_mean": -0.3565139434225078,
                "size": 406
            }
        },
        {
            "bounds": [
                7081,
                7141
            ],
            "type": "static",
            "stats": {
                "scale_mean": 1.0028929897870682,
                "tx_mean": -0.03289459106260613,
                "ty_mean": -2.107978326540974,
                "size": 84
            }
        },
        {
            "bounds": [
                7151,
                7411
            ],
            "type": "S",
            "stat": {
                "scale_mean": 0.9977806485589537,
                "tx_mean": -5.584762908405915,
                "ty_mean": -41.040851600539604,
                "size": 364
            }
        },
        {
            "bounds": [
                7411,
                7651
            ],
            "type": "static",
            "stats": {
                "scale_mean": 0.9999821869452162,
                "tx_mean": 1.29350104264572,
                "ty_mean": 0.5838573648631394,
                "size": 336
            }
        },
        {
            "bounds": [
                7661,
                7911
            ],
            "type": "N",
            "stat": {
                "scale_mean": 1.00543819182271,
                "tx_mean": -9.672559540813952,
                "ty_mean": 37.24717354506209,
                "size": 350
            }
        },
        {
            "bounds": [
                7911,
                8231
            ],
            "type": "static",
            "stats": {
                "scale_mean": 1.0002330127135561,
                "tx_mean": 1.0474508538237717,
                "ty_mean": 0.6230311255801357,
                "size": 448
            }
        },
        {
            "bounds": [
                8241,
                8401
            ],
            "type": "zoom_in",
            "stat": {
                "scale_mean": 1.0529324732233776,
                "tx_mean": -9.2641531637771,
                "ty_mean": 2.273726945230764,
                "size": 224
            }
        },
        {
            "bounds": [
                8401,
                8531
            ],
            "type": "static",
            "stats": {
                "scale_mean": 0.9999908619488328,
                "tx_mean": -0.021173780193689953,
                "ty_mean": 0.006176837916709323,
                "size": 182
            }
        },
        {
            "bounds": [
                8541,
                8681
            ],
            "type": "zoom_in",
            "stat": {
                "scale_mean": 1.0838403043728022,
                "tx_mean": 0.19013361047922414,
                "ty_mean": -1.9824576997993872,
                "size": 196
            }
        },
        {
            "bounds": [
                8681,
                9581
            ],
            "type": "static",
            "stats": {
                "scale_mean": 0.9999884903735792,
                "tx_mean": -0.014592654998195302,
                "ty_mean": 0.009073109737935977,
                "size": 1260
            }
        },
        {
            "bounds": [
                9591,
                9891
            ],
            "type": "zoom_out",
            "stat": {
                "scale_mean": 0.9359198254957612,
                "tx_mean": 4.664235830698428,
                "ty_mean": -1.5149715783307172,
                "size": 420
            }
        },
        {
            "bounds": [
                9891,
                9951
            ],
            "type": "static",
            "stats": {
                "scale_mean": 0.9993776572377041,
                "tx_mean": -0.309726251121571,
                "ty_mean": 0.2578965917324088,
                "size": 84
            }
        },
        {
            "bounds": [
                9961,
                10221
            ],
            "type": "S",
            "stat": {
                "scale_mean": 0.9943110978312195,
                "tx_mean": 5.717634756206386,
                "ty_mean": -42.30963568267967,
                "size": 364
            }
        },
        {
            "bounds": [
                10221,
                10531
            ],
            "type": "static",
            "stats": {
                "scale_mean": 1.0000071148960126,
                "tx_mean": -0.05038690174558108,
                "ty_mean": -0.38170013408588666,
                "size": 434
            }
        },
        {
            "bounds": [
                10541,
                10731
            ],
            "type": "NE",
            "stat": {
                "scale_mean": 1.0052699881263374,
                "tx_mean": -22.733948793608054,
                "ty_mean": 32.19456585935999,
                "size": 266
            }
        },
        {
            "bounds": [
                10731,
                11071
            ],
            "type": "static",
            "stats": {
                "scale_mean": 0.9997792451085981,
                "tx_mean": 0.8920939358006795,
                "ty_mean": 0.5052882420180203,
                "size": 476
            }
        },
        {
            "bounds": [
                11081,
                11241
            ],
            "type": "zoom_in",
            "stat": {
                "scale_mean": 1.0595776067473637,
                "tx_mean": -6.430719730982972,
                "ty_mean": -1.6664092685542087,
                "size": 224
            }
        },
        {
            "bounds": [
                11241,
                11371
            ],
            "type": "static",
            "stats": {
                "scale_mean": 0.9999891132717441,
                "tx_mean": 0.002220184694300554,
                "ty_mean": -0.0038467140071554795,
                "size": 182
            }
        },
        {
            "bounds": [
                11381,
                11531
            ],
            "type": "zoom_in",
            "stat": {
                "scale_mean": 1.0776890677050666,
                "tx_mean": 0.11192232813956189,
                "ty_mean": -2.4452358347453065,
                "size": 210
            }
        },
        {
            "bounds": [
                11531,
                12431
            ],
            "type": "static",
            "stats": {
                "scale_mean": 1.0000218052946,
                "tx_mean": 0.024031290947022586,
                "ty_mean": 0.031587741845718144,
                "size": 1260
            }
        },
        {
            "bounds": [
                12441,
                12731
            ],
            "type": "zoom_out",
            "stat": {
                "scale_mean": 0.9301616782650864,
                "tx_mean": 3.059086543910551,
                "ty_mean": 1.061713721605116,
                "size": 406
            }
        },
        {
            "bounds": [
                12731,
                12791
            ],
            "type": "static",
            "stats": {
                "scale_mean": 1.0002894267476636,
                "tx_mean": 0.24984979669077298,
                "ty_mean": -0.06651870928827254,
                "size": 84
            }
        },
        {
            "bounds": [
                12801,
                12981
            ],
            "type": "SW",
            "stat": {
                "scale_mean": 0.9937423879255495,
                "tx_mean": 20.399362165292697,
                "ty_mean": -39.2020774559567,
                "size": 252
            }
        },
        {
            "bounds": [
                12981,
                12991
            ],
            "type": "static",
            "stats": {
                "scale_mean": 1.0003878082548,
                "tx_mean": 7.03567538641117,
                "ty_mean": -6.84915519479064,
                "size": 14
            }
        },
        {
            "bounds": [
                13001,
                13021
            ],
            "type": "unknown",
            "stat": {
                "scale_mean": 1.000156146134195,
                "tx_mean": 7.42854001497459,
                "ty_mean": -6.758201422121085,
                "size": 28
            }
        },
        {
            "bounds": [
                13021,
                13301
            ],
            "type": "static",
            "stats": {
                "scale_mean": 1.0000024742473832,
                "tx_mean": -1.9606094291349214,
                "ty_mean": 0.3211830096771884,
                "size": 392
            }
        },
        {
            "bounds": [
                13311,
                13441
            ],
            "type": "SW",
            "stat": {
                "scale_mean": 1.0039390918753162,
                "tx_mean": 33.99764591863633,
                "ty_mean": -12.165568320664848,
                "size": 182
            }
        },
        {
            "bounds": [
                13441,
                13801
            ],
            "type": "static",
            "stats": {
                "scale_mean": 1.0000084960205486,
                "tx_mean": -0.01479725015049692,
                "ty_mean": 0.4657628072301658,
                "size": 504
            }
        },
        {
            "bounds": [
                13811,
                13971
            ],
            "type": "zoom_in",
            "stat": {
                "scale_mean": 1.0675457978138363,
                "tx_mean": 2.551234172119399,
                "ty_mean": -0.978252888986397,
                "size": 224
            }
        },
        {
            "bounds": [
                13971,
                14101
            ],
            "type": "static",
            "stats": {
                "scale_mean": 1.0000260889961867,
                "tx_mean": 0.04887705168634453,
                "ty_mean": 0.0023665180571894066,
                "size": 182
            }
        },
        {
            "bounds": [
                14111,
                14261
            ],
            "type": "zoom_in",
            "stat": {
                "scale_mean": 1.078456907699452,
                "tx_mean": 0.9328501306482,
                "ty_mean": -2.0333260494330174,
                "size": 210
            }
        },
        {
            "bounds": [
                14261,
                15161
            ],
            "type": "static",
            "stats": {
                "scale_mean": 0.9999983626549737,
                "tx_mean": 0.0013560422100480948,
                "ty_mean": -0.00044348076182425364,
                "size": 1260
            }
        },
        {
            "bounds": [
                15171,
                15461
            ],
            "type": "zoom_out",
            "stat": {
                "scale_mean": 0.9260639639557641,
                "tx_mean": -2.178120916517659,
                "ty_mean": 0.8392492277607717,
                "size": 406
            }
        },
        {
            "bounds": [
                15461,
                15521
            ],
            "type": "static",
            "stats": {
                "scale_mean": 1.0000358154921032,
                "tx_mean": -0.06231121553497195,
                "ty_mean": 0.0009913249791509836,
                "size": 84
            }
        },
        {
            "bounds": [
                15531,
                15661
            ],
            "type": "NE",
            "stat": {
                "scale_mean": 0.9971913132336299,
                "tx_mean": -33.97201270503312,
                "ty_mean": 12.612672471702979,
                "size": 182
            }
        },
        {
            "bounds": [
                15661,
                16151
            ],
            "type": "static",
            "stats": {
                "scale_mean": 1.0000334688617005,
                "tx_mean": -0.04983393905660739,
                "ty_mean": -0.606149606586542,
                "size": 686
            }
        },
        {
            "bounds": [
                16161,
                16321
            ],
            "type": "zoom_in",
            "stat": {
                "scale_mean": 1.0675212512354588,
                "tx_mean": 1.7039129832077027,
                "ty_mean": -1.679141901383953,
                "size": 224
            }
        },
        {
            "bounds": [
                16321,
                16451
            ],
            "type": "static",
            "stats": {
                "scale_mean": 0.9999452820924815,
                "tx_mean": 0.014463101279242281,
                "ty_mean": -0.02318964667287625,
                "size": 182
            }
        },
        {
            "bounds": [
                16461,
                16601
            ],
            "type": "zoom_in",
            "stat": {
                "scale_mean": 1.083121706301124,
                "tx_mean": 1.603272451518784,
                "ty_mean": -2.3379426686747036,
                "size": 196
            }
        },
        {
            "bounds": [
                16601,
                17501
            ],
            "type": "static",
            "stats": {
                "scale_mean": 1.0000455517600184,
                "tx_mean": 0.04251112385004769,
                "ty_mean": -0.006822313452115688,
                "size": 1260
            }
        },
        {
            "bounds": [
                17511,
                17811
            ],
            "type": "zoom_out",
            "stat": {
                "scale_mean": 0.9283246652216662,
                "tx_mean": -1.3507283878298375,
                "ty_mean": 1.0829836095510805,
                "size": 420
            }
        },
        {
            "bounds": [
                17811,
                18161
            ],
            "type": "static",
            "stats": {
                "scale_mean": 1.0000003778044195,
                "tx_mean": 0.0024368231966771024,
                "ty_mean": 0.6995028899745374,
                "size": 490
            }
        },
        {
            "bounds": [
                18171,
                18521
            ],
            "type": "S",
            "stat": {
                "scale_mean": 1.0030308030020105,
                "tx_mean": -0.054914054956390915,
                "ty_mean": -52.094141162658275,
                "size": 490
            }
        },
        {
            "bounds": [
                18521,
                18651
            ],
            "type": "static",
            "stats": {
                "scale_mean": 0.9999066849108419,
                "tx_mean": 0.0006419176829310629,
                "ty_mean": 2.024879794003362,
                "size": 182
            }
        },
        {
            "bounds": [
                18661,
                18671
            ],
            "type": "N",
            "stat": {
                "scale_mean": 1.00089079204393,
                "tx_mean": -2.48718766369087,
                "ty_mean": 50.6147095837047,
                "size": 14
            }
        },
        {
            "bounds": [
                18671,
                18961
            ],
            "type": "static",
            "stats": {
                "scale_mean": 0.9999996912870948,
                "tx_mean": -0.0034271425205530874,
                "ty_mean": -0.011682040635592743,
                "size": 406
            }
        },
        {
            "bounds": [
                18971,
                19161
            ],
            "type": "zoom_in",
            "stat": {
                "scale_mean": 1.073695685936257,
                "tx_mean": 1.7732478076551874,
                "ty_mean": -1.9751331878483824,
                "size": 266
            }
        },
        {
            "bounds": [
                19161,
                20051
            ],
            "type": "static",
            "stats": {
                "scale_mean": 1.0000096052254195,
                "tx_mean": 0.005469061209644929,
                "ty_mean": -0.005655853487090577,
                "size": 1246
            }
        },
        {
            "bounds": [
                20061,
                20251
            ],
            "type": "zoom_out",
            "stat": {
                "scale_mean": 0.9297096561676716,
                "tx_mean": -1.5340367943847022,
                "ty_mean": 1.077557960266331,
                "size": 266
            }
        },
        {
            "bounds": [
                20251,
                20411
            ],
            "type": "static",
            "stats": {
                "scale_mean": 0.9999880701063155,
                "tx_mean": -0.010087950040707092,
                "ty_mean": -0.0010149744643494123,
                "size": 224
            }
        },
        {
            "bounds": [
                20421,
                20761
            ],
            "type": "N",
            "stat": {
                "scale_mean": 0.995098638826503,
                "tx_mean": -0.09502191188623864,
                "ty_mean": 48.078564362636726,
                "size": 476
            }
        },
        {
            "bounds": [
                20761,
                21081
            ],
            "type": "static",
            "stats": {
                "scale_mean": 0.999998591682126,
                "tx_mean": 0.019731090705290583,
                "ty_mean": 0.5822215306317498,
                "size": 448
            }
        },
        {
            "bounds": [
                21091,
                21271
            ],
            "type": "SE",
            "stat": {
                "scale_mean": 0.9994570173202545,
                "tx_mean": -41.523957896083814,
                "ty_mean": -36.403048113350685,
                "size": 252
            }
        },
        {
            "bounds": [
                21271,
                21621
            ],
            "type": "static",
            "stats": {
                "scale_mean": 0.9999976013060847,
                "tx_mean": -0.16621599425953415,
                "ty_mean": 0.5955364867732206,
                "size": 490
            }
        },
        {
            "bounds": [
                21631,
                21751
            ],
            "type": "zoom_in",
            "stat": {
                "scale_mean": 1.064375085702791,
                "tx_mean": 1.0681251460440686,
                "ty_mean": -1.1754963332622699,
                "size": 168
            }
        },
        {
            "bounds": [
                21751,
                22631
            ],
            "type": "static",
            "stats": {
                "scale_mean": 0.9999980116231899,
                "tx_mean": -0.004276040128327239,
                "ty_mean": -0.0007399780344384203,
                "size": 1232
            }
        },
        {
            "bounds": [
                22641,
                22761
            ],
            "type": "zoom_out",
            "stat": {
                "scale_mean": 0.9378429193080109,
                "tx_mean": -1.0880106096450597,
                "ty_mean": 0.5664506142999273,
                "size": 168
            }
        },
        {
            "bounds": [
                22761,
                23141
            ],
            "type": "static",
            "stats": {
                "scale_mean": 1.0000015875677921,
                "tx_mean": 0.00539034631527548,
                "ty_mean": -0.003992145712556452,
                "size": 532
            }
        },
        {
            "bounds": [
                23151,
                23321
            ],
            "type": "NW",
            "stat": {
                "scale_mean": 0.9985334370676813,
                "tx_mean": 44.2391709980836,
                "ty_mean": 37.28077617355475,
                "size": 238
            }
        },
        {
            "bounds": [
                23321,
                23351
            ],
            "type": "static",
            "stats": {
                "scale_mean": 0.9999398658324914,
                "tx_mean": 7.157093104668527,
                "ty_mean": 6.387450315739101,
                "size": 42
            }
        },
        {
            "bounds": [
                23361,
                23371
            ],
            "type": "unknown",
            "stat": {
                "scale_mean": 0.999846398528417,
                "tx_mean": 7.53397784474639,
                "ty_mean": 6.72899710553871,
                "size": 14
            }
        },
        {
            "bounds": [
                23371,
                23661
            ],
            "type": "static",
            "stats": {
                "scale_mean": 1.0000121985254784,
                "tx_mean": -0.23984553802018616,
                "ty_mean": -1.046988397962817,
                "size": 406
            }
        },
        {
            "bounds": [
                23671,
                23841
            ],
            "type": "S",
            "stat": {
                "scale_mean": 1.0010627453513323,
                "tx_mean": -0.18936194842663867,
                "ty_mean": -42.799509158056495,
                "size": 238
            }
        },
        {
            "bounds": [
                23841,
                24111
            ],
            "type": "static",
            "stats": {
                "scale_mean": 1.0000224497987285,
                "tx_mean": -0.006913098261779153,
                "ty_mean": -0.4617134421307969,
                "size": 378
            }
        }
    ]
}